LICENSE
dockerautotag/__init__.py
dockerautotag/cli.py
dockerautotag/logging.py
dockerautotag/utils.py
docker_autotag-3.0.0.dist-info/LICENSE
docker_autotag-3.0.0.dist-info/METADATA
docker_autotag-3.0.0.dist-info/WHEEL
docker_autotag-3.0.0.dist-info/entry_points.txt
docker_autotag-3.0.0.dist-info/RECORD
