Metadata-Version: 2.1
Name: docker-autotag
Version: 3.0.0
Summary: Creates a list of docker tags from a given version string.
Home-page: https://github.com/thegeeklab/docker-autotag/
License: MIT
Keywords: docker,versioning,automation,ci
Author: Robert Kaussow
Author-email: mail@thegeeklab.de
Requires-Python: >=3.10.0,<4.0.0
Classifier: Development Status :: 5 - Production/Stable
Classifier: Environment :: Console
Classifier: Intended Audience :: Developers
Classifier: Intended Audience :: Information Technology
Classifier: Intended Audience :: System Administrators
Classifier: License :: OSI Approved :: MIT License
Classifier: Natural Language :: English
Classifier: Operating System :: POSIX
Classifier: Programming Language :: Python :: 3
Classifier: Programming Language :: Python :: 3.10
Classifier: Programming Language :: Python :: 3.11
Classifier: Programming Language :: Python :: 3.12
Classifier: Programming Language :: Python :: 3.13
Classifier: Topic :: Software Development
Classifier: Topic :: Utilities
Requires-Dist: colorama (==0.4.6)
Requires-Dist: python-json-logger (==2.0.7)
Requires-Dist: semantic-version (==2.10.0)
Project-URL: Documentation, https://github.com/thegeeklab/docker-autotag/
Project-URL: Repository, https://github.com/thegeeklab/docker-autotag/
